Epate/__init__.py
Epate/epate.py
Epate-1.5.0.dist-info/LICENSE
Epate-1.5.0.dist-info/METADATA
Epate-1.5.0.dist-info/WHEEL
Epate-1.5.0.dist-info/entry_points.txt
Epate-1.5.0.dist-info/top_level.txt
Epate-1.5.0.dist-info/RECORD
